CHANGES.txt
README.txt
icon.ico
setup.cfg
setup.py
setup_cx.py
tox.ini
docs/Makefile
docs/make.bat
docs/source/conf.py
docs/source/index.rst
docs/source/library.rst
docs/source/readme.rst
elfcloud/__init__.py
elfcloud/client.py
elfcloud/connection.py
elfcloud/container.py
elfcloud/dataitem.py
elfcloud/exceptions.py
elfcloud/filecrypt.py
elfcloud/utils.py
elfcloud/cli/__init__.py
elfcloud/tests/__init__.py
elfcloud/tests/cli.py
elfcloud/tests/client.py
elfcloud/tests/connection.py
elfcloud/tests/container.py
elfcloud/tests/dataitem.py
elfcloud/tests/filecrypt.py
elfcloud/tests/utils.py
elfcloud_weasel.egg-info/PKG-INFO
elfcloud_weasel.egg-info/SOURCES.txt
elfcloud_weasel.egg-info/dependency_links.txt
elfcloud_weasel.egg-info/entry_points.txt
elfcloud_weasel.egg-info/requires.txt
elfcloud_weasel.egg-info/top_level.txt
elfcloud_weasel.egg-info/zip-safe