Metadata-Version: 1.0
Name: elfcloud-weasel
Version: 1.1
Summary: elfCLOUD.fi Weasel
Home-page: http://elfcloud.fi/
Author: elfCLOUD
Author-email: support.dev@elfcloud.fi
License: UNKNOWN
Platform: UNKNOWN
Classifier: Programming Language :: Python
Classifier: Topic :: Internet :: WWW/HTTP
Classifier: Topic :: Software Development :: Libraries :: Python Modules
Classifier: Topic :: System :: Distributed Computing
Classifier: Topic :: Utilities
